niflow/__init__.py
niflow/nipype1/__init__.py
niflow/nipype1/workflows/__init__.py
niflow/nipype1/workflows/cli.py
niflow/nipype1/workflows/data/__init__.py
niflow/nipype1/workflows/data/ecc.sch
niflow/nipype1/workflows/data/hmc.sch
niflow/nipype1/workflows/dmri/__init__.py
niflow/nipype1/workflows/dmri/camino/__init__.py
niflow/nipype1/workflows/dmri/camino/connectivity_mapping.py
niflow/nipype1/workflows/dmri/camino/diffusion.py
niflow/nipype1/workflows/dmri/camino/group_connectivity.py
niflow/nipype1/workflows/dmri/connectivity/__init__.py
niflow/nipype1/workflows/dmri/connectivity/group_connectivity.py
niflow/nipype1/workflows/dmri/connectivity/nx.py
niflow/nipype1/workflows/dmri/dipy/__init__.py
niflow/nipype1/workflows/dmri/dipy/denoise.py
niflow/nipype1/workflows/dmri/dtitk/__init__.py
niflow/nipype1/workflows/dmri/dtitk/tensor_registration.py
niflow/nipype1/workflows/dmri/fsl/__init__.py
niflow/nipype1/workflows/dmri/fsl/artifacts.py
niflow/nipype1/workflows/dmri/fsl/dti.py
niflow/nipype1/workflows/dmri/fsl/epi.py
niflow/nipype1/workflows/dmri/fsl/tbss.py
niflow/nipype1/workflows/dmri/fsl/utils.py
niflow/nipype1/workflows/dmri/fsl/tests/__init__.py
niflow/nipype1/workflows/dmri/fsl/tests/test_dti.py
niflow/nipype1/workflows/dmri/fsl/tests/test_epi.py
niflow/nipype1/workflows/dmri/fsl/tests/test_tbss.py
niflow/nipype1/workflows/dmri/mrtrix/__init__.py
niflow/nipype1/workflows/dmri/mrtrix/connectivity_mapping.py
niflow/nipype1/workflows/dmri/mrtrix/diffusion.py
niflow/nipype1/workflows/dmri/mrtrix/group_connectivity.py
niflow/nipype1/workflows/fmri/__init__.py
niflow/nipype1/workflows/fmri/fsl/__init__.py
niflow/nipype1/workflows/fmri/fsl/estimate.py
niflow/nipype1/workflows/fmri/fsl/preprocess.py
niflow/nipype1/workflows/fmri/fsl/tests/__init__.py
niflow/nipype1/workflows/fmri/fsl/tests/test_preprocess.py
niflow/nipype1/workflows/fmri/spm/__init__.py
niflow/nipype1/workflows/fmri/spm/estimate.py
niflow/nipype1/workflows/fmri/spm/preprocess.py
niflow_nipype1_workflows-0.0.5.dist-info/METADATA
niflow_nipype1_workflows-0.0.5.dist-info/WHEEL
niflow_nipype1_workflows-0.0.5.dist-info/entry_points.txt
niflow_nipype1_workflows-0.0.5.dist-info/top_level.txt
niflow_nipype1_workflows-0.0.5.dist-info/RECORD
