Metadata-Version: 2.1
Name: niflow-nipype1-workflows
Version: 0.0.5
Summary: niflow-nipype1-workflows workflow package
Home-page: https://github.com/niflows/nipype1-workflows
Author: nipype developers
Author-email: neuroimaging@python.org
Maintainer: nipype developers
Maintainer-email: neuroimaging@python.org
License: Apache License, 2.0
Platform: UNKNOWN
Classifier: Development Status :: 2 - Pre-Alpha
Classifier: Environment :: Console
Classifier: Intended Audience :: Developers
Classifier: License :: OSI Approved :: Apache Software License
Classifier: Operating System :: OS Independent
Classifier: Programming Language :: Python :: 3
Classifier: Topic :: Scientific/Engineering
Requires-Dist: nipype
Requires-Dist: future (>=0.16.0)
Requires-Dist: Click
